[
  {
    "type": "post",
    "postAuthor": "Merdan Bayramov",
    "postTitle": "Do you have to have DFY service before becoming an educational community?",
    "postBodyPreview": "8d  • 🤑 MonetizationDo you have to have DFY service before becoming an educational community?Hey everyone!Do you think you have to have Done for you service before you can run a community that is educational mostly maybe with some done-with-you services?Assuming, there is a little bit of evidence o",
    "postHref": "https://www.skool.com/synthesizer/do-you-have-to-have-dfy-service-before-becoming-an-educational-community",
    "tags": {
      "tone_tags": [],
      "intent": "value-flex",
      "sales_stage": "nurture",
      "reasoning": "label=value-flex topic=coaching-philosophy flex_score=3 — Questions the need for DFY services to lead an educational community."
    },
    "reply": "I don't think you need a DFY offer. There are many ways to build proof besides doing the work for your clients.",
    "timestamp": "2026-04-30T06:34:12.358Z"
  }
]